xia_engine_gitlab/__init__.py
xia_engine_gitlab/engine.cpython-311-darwin.so
xia_engine_gitlab/engine_code.cpython-311-darwin.so
xia_engine_gitlab/engine_discussion.cpython-311-darwin.so
xia_engine_gitlab/engine_group.cpython-311-darwin.so
xia_engine_gitlab/engine_issue.cpython-311-darwin.so
xia_engine_gitlab/engine_merge_request.cpython-311-darwin.so
xia_engine_gitlab/engine_milestone.cpython-311-darwin.so
xia_engine_gitlab/engine_notes.cpython-311-darwin.so
xia_engine_gitlab/engine_project.cpython-311-darwin.so
xia_engine_gitlab/engine_snippet.cpython-311-darwin.so
xia_engine_gitlab/engine_wiki.cpython-311-darwin.so
xia_engine_gitlab-0.0.30.dist-info/LICENSE.txt
xia_engine_gitlab-0.0.30.dist-info/METADATA
xia_engine_gitlab-0.0.30.dist-info/WHEEL
xia_engine_gitlab-0.0.30.dist-info/top_level.txt
xia_engine_gitlab-0.0.30.dist-info/RECORD
