Metadata-Version: 2.1
Name: xia-engine-gitlab
Version: 0.0.30
Home-page: https://develop.x-i-a.com/docs/xia-engine-gitlab/0.0.30/index.html
Author: X-I-A
Author-email: admin@x-i-a.com
Requires-Python: >=3.9
License-File: LICENSE.txt
Requires-Dist: requests
Requires-Dist: PyYAML
Requires-Dist: xia-engine
